error_wrapper/__init__.py
error_wrapper/error_wrapper.py
error_wrapper-0.9.6.dist-info/METADATA
error_wrapper-0.9.6.dist-info/WHEEL
error_wrapper-0.9.6.dist-info/top_level.txt
error_wrapper-0.9.6.dist-info/RECORD
