Metadata-Version: 2.1
Name: error-wrapper
Version: 0.9.6
Summary: Error wrapper with auto logging
Home-page: https://github.com/glavmotor/error-wrapper
Author: Dmitry Kravtsov
License: MIT
Platform: UNKNOWN
